qfetch/__init__.py
qfetch/qfetch.py
qfetch_py-1.0.0.dist-info/LICENSE
qfetch_py-1.0.0.dist-info/METADATA
qfetch_py-1.0.0.dist-info/WHEEL
qfetch_py-1.0.0.dist-info/entry_points.txt
qfetch_py-1.0.0.dist-info/top_level.txt
qfetch_py-1.0.0.dist-info/RECORD
