Metadata-Version: 2.1
Name: qfetch-py
Version: 1.0.0
Summary: a simple, no-fuss System Information CLI tool written in Python (Designed/Tested for Ubuntu, Debian, and MacOS)
Home-page: https://github.com/qvipin/qfetch
Author: Vipin B
Author-email: vipin@vipin.xyz
Classifier: Programming Language :: Python :: 3
Classifier: Operating System :: POSIX :: Linux
Classifier: Operating System :: MacOS
Classifier: Intended Audience :: Developers
Classifier: Environment :: Console
Classifier: Topic :: System :: Monitoring
Requires-Python: >=3.12
License-File: LICENSE
